tblfaker/__init__.py
tblfaker/__version__.py
tblfaker/_common.py
tblfaker/_tblfaker.py
tblfaker/py.typed
tblfaker-1.0.0.dist-info/LICENSE
tblfaker-1.0.0.dist-info/METADATA
tblfaker-1.0.0.dist-info/WHEEL
tblfaker-1.0.0.dist-info/top_level.txt
tblfaker-1.0.0.dist-info/zip-safe
tblfaker-1.0.0.dist-info/RECORD
